tests/__init__.py
tests/test_collectors.py
uwsgi_prometheus/__init__.py
uwsgi_prometheus/collectors.py
uwsgi_prometheus-1.0.0.dist-info/LICENSE
uwsgi_prometheus-1.0.0.dist-info/METADATA
uwsgi_prometheus-1.0.0.dist-info/WHEEL
uwsgi_prometheus-1.0.0.dist-info/top_level.txt
uwsgi_prometheus-1.0.0.dist-info/RECORD
