Metadata-Version: 2.1
Name: uwsgi-prometheus
Version: 1.0.0
Summary: uWSGI stats exporter for Prometheus
Home-page: https://github.com/GlobalRadio/uwsgi-prometheus
Author: Chris Graham
Author-email: chris.graham@global.com
License: MIT
Classifier: Natural Language :: English
Classifier: License :: OSI Approved :: MIT License
Classifier: Programming Language :: Python
Classifier: Programming Language :: Python :: 3
Classifier: Programming Language :: Python :: 3.8
Classifier: Programming Language :: Python :: 3.9
Classifier: Programming Language :: Python :: 3.10
Classifier: Programming Language :: Python :: 3.11
Classifier: Programming Language :: Python :: 3.12
Requires-Python: >=3.8
License-File: LICENSE
Requires-Dist: prometheus-client
Requires-Dist: requests
